{
  "main": {
    "id": "3fce3eced54956d3",
    "type": "split",
    "children": [
      {
        "id": "d325410f2ccedcd3",
        "type": "tabs",
        "children": [
          {
            "id": "5a9674a3f7bab427",
            "type": "leaf",
            "state": {
              "type": "markdown",
              "state": {
                "file": "2023-01-04.md",
                "mode": "source",
                "source": false
              }
            }
          }
        ]
      }
    ],
    "direction": "vertical"
  },
  "left": {
    "id": "48678900d4bfc52a",
    "type": "split",
    "children": [
      {
        "id": "0f4ecf1d9897d7a5",
        "type": "tabs",
        "children": [
          {
            "id": "70bc21bce1e58650",
            "type": "leaf",
            "state": {
              "type": "file-explorer",
              "state": {
                "sortOrder": "alphabetical"
              }
            }
          },
          {
            "id": "6528e87b065e6be3",
            "type": "leaf",
            "state": {
              "type": "search",
              "state": {
                "query": "",
                "matchingCase": false,
                "explainSearch": false,
                "collapseAll": false,
                "extraContext": false,
                "sortOrder": "alphabetical"
              }
            }
          },
          {
            "id": "61520701967d1270",
            "type": "leaf",
            "state": {
              "type": "starred",
              "state": {}
            }
          }
        ]
      }
    ],
    "direction": "horizontal",
    "width": 300
  },
  "right": {
    "id": "89026a917249ad34",
    "type": "split",
    "children": [
      {
        "id": "8b5b02ee630607f8",
        "type": "tabs",
        "children": [
          {
            "id": "122cf32085a7c287",
            "type": "leaf",
            "state": {
              "type": "backlink",
              "state": {
                "file": "2023-01-04.md",
                "collapseAll": false,
                "extraContext": false,
                "sortOrder": "alphabetical",
                "showSearch": false,
                "searchQuery": "",
                "backlinkCollapsed": false,
                "unlinkedCollapsed": true
              }
            }
          },
          {
            "id": "79a20faf540787c1",
            "type": "leaf",
            "state": {
              "type": "outgoing-link",
              "state": {
                "file": "2023-01-04.md",
                "linksCollapsed": false,
                "unlinkedCollapsed": true
              }
            }
          },
          {
            "id": "5e1cea90e850ae10",
            "type": "leaf",
            "state": {
              "type": "tag",
              "state": {
                "sortOrder": "frequency",
                "useHierarchy": true
              }
            }
          },
          {
            "id": "8412caba90121330",
            "type": "leaf",
            "state": {
              "type": "outline",
              "state": {
                "file": "2023-01-04.md"
              }
            }
          }
        ]
      }
    ],
    "direction": "horizontal",
    "width": 300,
    "collapsed": true
  },
  "left-ribbon": {
    "hiddenItems": {
      "switcher:Open quick switcher": false,
      "graph:Open graph view": false,
      "canvas:Create new canvas": false,
      "daily-notes:Open today's daily note": false,
      "templates:Insert template": false,
      "command-palette:Open command palette": false
    }
  },
  "active": "5a9674a3f7bab427",
  "lastOpenFiles": [
    "Untitled.canvas",
    "Untitled.md"
  ]
}